pptx_ea_font-0.0.4.dist-info/METADATA
pptx_ea_font-0.0.4.dist-info/WHEEL
pptx_ea_font-0.0.4.dist-info/entry_points.txt
pptx_ea_font-0.0.4.dist-info/licenses/LICENSE
pptx_ea_font/__init__.py
pptx_ea_font-0.0.4.dist-info/RECORD
